mgkit/__init__.py
mgkit/align.py
mgkit/consts.py
mgkit/graphs.py
mgkit/kegg.py
mgkit/logger.py
mgkit/simple_cache.py
mgkit/taxon.py
mgkit/counts/__init__.py
mgkit/counts/func.py
mgkit/counts/glm.py
mgkit/counts/scaling.py
mgkit/db/__init__.py
mgkit/db/dbm.py
mgkit/db/mongo.py
mgkit/filter/__init__.py
mgkit/filter/common.py
mgkit/filter/gff.py
mgkit/filter/lists.py
mgkit/filter/reads.py
mgkit/filter/taxon.py
mgkit/io/__init__.py
mgkit/io/blast.py
mgkit/io/fasta.py
mgkit/io/fastq.py
mgkit/io/gff.py
mgkit/io/glimmer.py
mgkit/io/snpdat.py
mgkit/io/uniprot.py
mgkit/io/utils.py
mgkit/mappings/__init__.py
mgkit/mappings/cazy.py
mgkit/mappings/eggnog.py
mgkit/mappings/enzyme.py
mgkit/mappings/go.py
mgkit/mappings/pandas_map.py
mgkit/mappings/taxon.py
mgkit/mappings/utils.py
mgkit/net/__init__.py
mgkit/net/embl.py
mgkit/net/pfam.py
mgkit/net/uniprot.py
mgkit/net/utils.py
mgkit/plots/__init__.py
mgkit/plots/abund.py
mgkit/plots/boxplot.py
mgkit/plots/colors.py
mgkit/plots/heatmap.py
mgkit/plots/unused.py
mgkit/plots/utils.py
mgkit/snps/__init__.py
mgkit/snps/classes.py
mgkit/snps/conv_func.py
mgkit/snps/filter.py
mgkit/snps/funcs.py
mgkit/snps/mapper.py
mgkit/utils/__init__.py
mgkit/utils/_sequence.cpython-38-darwin.so
mgkit/utils/common.py
mgkit/utils/dictionary.py
mgkit/utils/sequence.py
mgkit/utils/trans_tables.py
mgkit/workflow/__init__.py
mgkit/workflow/add_gff_info.py
mgkit/workflow/alg_utils.py
mgkit/workflow/blast2gff.py
mgkit/workflow/count_utils.py
mgkit/workflow/dict_utils.py
mgkit/workflow/edit_gff.py
mgkit/workflow/extract_gff_info.py
mgkit/workflow/fasta_utils.py
mgkit/workflow/fastq_utils.py
mgkit/workflow/filter_gff.py
mgkit/workflow/hmmer2gff.py
mgkit/workflow/json2gff.py
mgkit/workflow/pnps_gen.py
mgkit/workflow/sampling_utils.py
mgkit/workflow/snp_parser.py
mgkit/workflow/taxon_utils.py
mgkit/workflow/utils.py
mgkit-0.5.7.data/scripts/download-ncbi-taxa.sh
mgkit-0.5.7.data/scripts/download-taxonomy.sh
mgkit-0.5.7.data/scripts/download-uniprot-taxa.sh
mgkit-0.5.7.dist-info/LICENSE
mgkit-0.5.7.dist-info/LICENSE.txt
mgkit-0.5.7.dist-info/METADATA
mgkit-0.5.7.dist-info/WHEEL
mgkit-0.5.7.dist-info/entry_points.txt
mgkit-0.5.7.dist-info/top_level.txt
mgkit-0.5.7.dist-info/RECORD
