Metadata-Version: 2.1
Name: mgkit
Version: 0.5.7
Summary: Metagenomics Framework
Home-page: https://github.com/frubino/mgkit
Author: Francesco Rubino
Author-email: rubino.francesco@gmail.com
License: GPL2+
Keywords: metagenomics library biology bioinformatics snps gff fasta
Platform: UNKNOWN
Classifier: Development Status :: 5 - Production/Stable
Classifier: Environment :: Console
Classifier: Intended Audience :: Developers
Classifier: Intended Audience :: Science/Research
Classifier: License :: OSI Approved :: GNU General Public License v2 or later (GPLv2+)
Classifier: Natural Language :: English
Classifier: Operating System :: OS Independent
Classifier: Programming Language :: Python :: 3
Classifier: Topic :: Scientific/Engineering
Classifier: Topic :: Scientific/Engineering :: Bio-Informatics
Requires-Dist: numpy (>=1.19.2)
Requires-Dist: pandas (>=1.1.3)
Requires-Dist: tqdm (>=4.0)
Requires-Dist: semidbm (>=0.5.1)
Requires-Dist: pymongo (>=3.1.1)
Requires-Dist: pyarrow (>=2.0.0)
Requires-Dist: scipy (>=1.5.2)
Requires-Dist: matplotlib (>=2)
Requires-Dist: msgpack-python (>=0.5.6)
Requires-Dist: statsmodels (>=0.12)
Requires-Dist: networkx
Requires-Dist: future
Requires-Dist: requests
Requires-Dist: PyVCF (>=0.6.0)
Requires-Dist: click (>=6)
Requires-Dist: tables (>=3.4.2)
Requires-Dist: pysam (>=0.14)
Requires-Dist: enum34 ; python_version < "3.4"
